aws_sam_tools/__init__.py
aws_sam_tools/cfn_processing.py
aws_sam_tools/cfn_tags.py
aws_sam_tools/cli.py
aws_sam_tools/openapi.py
aws_sam_tools-0.1.2.dist-info/METADATA
aws_sam_tools-0.1.2.dist-info/WHEEL
aws_sam_tools-0.1.2.dist-info/entry_points.txt
aws_sam_tools-0.1.2.dist-info/RECORD
