Metadata-Version: 2.4
Name: aws-sam-tools
Version: 0.1.2
Project-URL: Homepage, https://github.com/martin-macak/aws-sam-tools
Project-URL: Repository, https://github.com/martin-macak/aws-sam-tools
Project-URL: Bug Tracker, https://github.com/martin-macak/aws-sam-tools/issues
Project-URL: Documentation, https://github.com/martin-macak/aws-sam-tools#readme
Author-email: Martin Macak <martin.macak@gmail.com>
Maintainer-email: Martin Macak <martin.macak@gmail.com>
License: MIT
Keywords: aws,debugger,debugging,development,lambda,serverless
Classifier: Development Status :: 4 - Beta
Classifier: Environment :: Console
Classifier: Intended Audience :: Developers
Classifier: License :: OSI Approved :: MIT License
Classifier: Operating System :: OS Independent
Classifier: Programming Language :: Python :: 3
Classifier: Programming Language :: Python :: 3.13
Requires-Python: >=3.13
Requires-Dist: click>=8.2.1
Requires-Dist: dunamai>=1.24.1
Requires-Dist: pyyaml>=6.0.2
